<?xml version='1.0' encoding="UTF-8"?>
<?xml-stylesheet href="/xsl/guide.xsl" type="text/xsl"?>
<!DOCTYPE guide SYSTEM "/dtd/guide.dtd">
<guide type="newsletter">
<title>Gentoo Weekly Newsletter</title>
<subtitle>9 Settembre 2003</subtitle>
<abstract>Questa è la Gentoo Weekly Newsletter per la settimana a partire dal 8 settembre 2003.</abstract>
<summary>Secondo successo per il Gentoo BugDay</summary>
<version>Anno 2, Numero 36</version>
<date>9 Settembre 2003</date>
<author title="Editor">
    <mail link="carlos@gentoo.org">Yuji Carlos Kosugi</mail>
</author>
<author title="Contributor">
    <mail link="aja@clanarmstrong.com">AJ Armstrong</mail>
</author>
<author title="Contributor">
	<mail link="bdowney@briandowney.net">Brian Downey</mail>
</author>
<author title="Contributor">
	<mail link="cal@calevans.com">Cal Evans</mail>
</author>
<author title="Contributor">
	<mail link="gubbs@fudo.org">Chris Gavin</mail>
</author>
<author title="Contributor">
	<mail link="cold_flame@email.com">Luke Giuliani</mail>
</author>
<author title="Contributor">
	<mail link="shawn.jonnet@verizon.net">Shawn Jonnet</mail>
</author>
<author title="Contributor">
	<mail link="citizen428@gentoo.org">Michael Kohl</mail>
</author>
<author title="Contributor">
	<mail link="klieber@gentoo.org">Kurt Lieber</mail>
</author>
<author title="Contributor">
    <mail link="rcm@sasaska.net">Rafael Cordones Marcos</mail>
</author>
<author title="Contributor">
    <mail link="david@phrixus.net">David Narayan</mail>
</author>
<author title="Contributor">
	<mail link="gerrynjr@gentoo.org">Gerald J Normandin Jr.</mail>
</author>
<author title="Contributor">
    <mail link="plate@gentoo.org">Ulrich Plate</mail>
</author>
<author title="Dutch Translation">
        <mail link="matje@lanzone.be">Mathy Vanvoorden</mail>
</author>
<author title="Dutch Translation">
        <mail link="Hendrik.Eeckhaut@UGent.be">Hendrik Eeckhaut</mail>
</author>
<author title="Dutch Translation">
        <mail link="sephiroth@quicknet.nl">Jorn Eilander</mail>
</author>
<author title="Dutch Translation">
        <mail link="bernieke@bernieke.com">Bernard Kerckenaere</mail>
</author>
<author title="Dutch Translation">
        <mail link="peter@daborg.nl">Peter ter Borg</mail>
</author>
<author title="Dutch Translation">
        <mail link="linux@sejo.be">Jochen Maes</mail>
</author>
<author title="Dutch Translation">
        <mail link="rgoessen@home.nl">Roderick Goessen</mail>
</author>
<author title="Dutch Translation">
        <mail link="gerard@steelo.net">Gerard van den Berg</mail>
</author>
<author title="French Translation">
    <mail link="mat@frheaven.com">Matthieu Montaudouin</mail>
</author>
<author title="French Translation">
    <mail link="riverdale@linuxmail.org">Martin Prieto</mail>
</author>
<author title="French Translation">
    <mail link="cabec2@pegase.net">Antoine Raillon</mail>
</author>
<author title="French Translation">
    <mail link="seb@cine7.net">Sebastien Cevey</mail>
</author>
<author title="French Translation">
    <mail link="mabouya@petitefleure.org">Jean-Christophe Choisy</mail>
</author>
<author title="German Translation">
	<mail link="madeagle@gentoo.org">Steffen Lassahn</mail>
</author>
<author title="German Translation">
	<mail link="haim@gentoo.org">Matthias F. Brandstetter</mail>
</author>
<author title="German Translation">
	<mail link="lordvan@gentoo.org">Thomas Raschbacher</mail>
</author>
<author title="German Translation">
	<mail link="yanestra@gentoo.org">Klaus-J. Wolf</mail>
</author>
<author title="Italian Translation">
	<mail link="mush@monrif.net">Marco Mascherpa</mail>
</author>
<author title="Italian Translation">
	<mail link="paper@tiscali.it">Claudio Merloni</mail>
</author>
<author title="Italian Translation">
	<mail link="bsolar@bluewin.ch">Christian Apolloni</mail>
</author>
<author title="Italian Translation">
	<mail link="stefano.lucidi@gentoo-italia.org">Stefano Lucidi</mail>
</author>
<author title="Japanese Translation">
	<mail link="hagi@p1d.com">Yoshiaki Hagihara</mail>
</author>
<author title="Japanese Translation">
	<mail link="katuyuki@siva.ddo.jp">Katsuyuki Konno</mail>
</author>
<author title="Japanese Translation">
	<mail link="carlos@gentoo.org">Yuji Carlos Kosugi</mail>
</author>
<author title="Japanese Translation">
	<mail link="yasunori@mail.portland.co.uk">Yasunori Fukudome</mail>
</author>
<author title="Japanese Translation">
    <mail link="088@t.email.ne.jp">Takashi Ota</mail>
</author>
<author title="Polish Translation">
    <mail link="sototh@gts.pl">Radoslaw Janeczko</mail>
</author>
<author title="Polish Translation">
    <mail link="lucass.home@pf.pl">Lukasz Strzygowski</mail>
</author>
<author title="Polish Translation">
    <mail link="veng@wp.pl">Michal Drobek</mail>
</author>
<author title="Polish Translation">
    <mail link="apo@cyberpunk.net.pulawy.pl">Adam Lyjak</mail>
</author>
<author title="Polish Translation">
    <mail link="cthulhu@emusearch.net">Krzysztof Klimonda</mail>
</author>
<author title="Portuguese (Brazil) Translation">
	<mail link="bohlke@inf.ufrgs.br">Atila "Jedi" Bohlke Vasconcelos</mail>
</author>
<author title="Portuguese (Brazil) Translation">
	<mail link="dudu@datavibe.net">Eduardo Belloti</mail>
</author>
<author title="Portuguese (Brazil) Translation">
	<mail link="joaoraf@rudah.com.br">Jo&#227;o Rafael Moraes Nicola</mail>
</author>
<author title="Portuguese (Brazil) Translation">
	<mail link="mgazambuja@terra.com.br">Marcelo Gon&#231;alves de Azambuja</mail>
</author>
<author title="Portuguese (Brazil) Translation">
	<mail link="angusy@gentoobr.org">Otavio Rodolfo Piske</mail>
</author>
<author title="Portuguese (Brazil) Translation">
	<mail link="natunobilis@gentoobr.org">Pablo N. Hess -- NatuNobilis</mail>
</author>
<author title="Portuguese (Brazil) Translation">
	<mail link="pzilla@yawl.com.br">Pedro de Medeiros</mail>
</author>
<author title="Portuguese (Brazil) Translation">
	<mail link="venturasbarbeiro@ig.com.br">Ventura Barbeiro</mail>
</author>
<author title="Portuguese (Portugal) Translation">
<mail link="blueroom@digitalmente.net">Bruno Ferreira</mail>
</author>
<author title="Portuguese (Portugal) Translation">
	<mail link="humpback@felisberto.net">Gustavo Felisberto</mail>
</author>
<author title="Portuguese (Portugal) Translation">
	<mail link="jose_costa@netcabo.pt">Jos&#233; Costa</mail>
</author>
<author title="Portuguese (Portugal) Translation">
	<mail link="metalgodin@linuxmail.org">Luis Medina</mail>
</author>
<author title="Portuguese (Portugal) Translation">
	<mail link="rjlouro@rjlouro.org">Ricardo Loureiro</mail>
</author>
<author title="Russian Translator">
       <mail link="gals_home@list.ru">Sergey Galkin</mail>
</author>
<author title="Russian Translator">
       <mail link="svyatogor@gentoo.org">Sergey Kuleshov</mail>
</author>
<author title="Russian Translator">
       <mail link="asp13@mail.ru">Alex Spirin</mail>
</author>
<author title="Russian Translator">
       <mail link="dimsuz@mail.ru">Dmitry Suzdalev</mail>
</author>
<author title="Russian Translator">
       <mail link="mazurous@mail.ru">Anton Vorovatov</mail>
</author>
<author title="Russian Translator">
       <mail link="dzaletov@rambler.ru">Denis Zaletov</mail>
</author>
<author title="Spanish Translation">
     <mail link="lanark@lanark.com.ar">Lanark</mail>
</author>
<author title="Spanish Translation">
     <mail link="ferdy@ferdyx.org">Fernando J. Pereda</mail>
</author>
<author title="Spanish Translation">
     <mail link="lpeinado@uoc.edu">Lluis Peinado Cifuentes</mail>
</author>
<author title="Spanish Translation">
     <mail link="ZEPHRYNXIRDAL@telefonica.net">Zephryn Xirdal T</mail>
</author>
<author title="Spanish Translation">
     <mail link="katossi@usuarios.retecal.es">Guillermo Juarez</mail>
</author>
<author title="Spanish Translation">
     <mail link="correo@sevein.com">Jes&#250;s Garc&#237;a Crespo</mail>
</author>
<author title="Spanish Translation">
     <mail link="carlos@castillobueno.com">Carlos Castillo</mail>
</author>
<author title="Spanish Translation">
     <mail link="julio@castillobueno.com">Julio Castillo</mail>
</author>
<author title="Spanish Translation">
     <mail link="s3r@fibertel.com.ar">Sergio G&#243;mez</mail>
</author>
<author title="Turkish Translation">
        <mail link="aycan@core.gen.tr">Aycan Irican</mail>
</author>
<author title="Turkish Translation">
        <mail link="bugra@myrealbox.com">Bugra Cakir</mail>
</author>
<author title="Turkish Translation">
        <mail link="cagils@biznet.com.tr">Cagil Seker</mail>
</author>
<author title="Turkish Translation">
        <mail link="emre@core.gen.tr">Emre Kazdagli</mail>
</author>
<author title="Turkish Translation">
        <mail link="evrim@core.gen.tr">Evrim Ulu</mail>
</author>
<author title="Turkish Translation">
        <mail link="gurcell@core.gen.tr">Gursel Kaynak</mail>
</author>
<chapter>
	<title>Gentoo News</title>
	<section>
		<title>Indice</title>
		<body>
			<ul>
				<li><uri link="#doc_chap1_sect2">Secondo successo per il Gentoo BugDay</uri></li>
			</ul>
		</body>
	</section>
<section>
	<title>Secondo successo per il Gentoo BugDay</title>
	<body>
	<p>
	Un altro grande successo: i partecipanti al BugDay di questa settimana, tenutosi il 6 Settembre hanno coraggiosamente
	risolto un totale di 124 bug. Al secondo mese di vita l'iniziativa BugDay ha raccolto un totale di 171 corretori di bug
	con un record di 143 partecipanti nel canale #gentoo-bugs, superando di un bel po' il primo BugDay (lo scorso mese avevano
	partecipato in 130). Tra la folla di partecipanti c'erano molti ansiosi di condividere la propria esperienza e imparare
	dagli altri. Gli utenti sono riusciti a collaborare con gli sviluppatori Gentoo in una maniera unica e sono stati scovati alcuni
	nuovi potenziali sviluppatori. Ringraziamo tutti quelli che hanno partecipato e reso il BugDay di questo mese un gigantesco
	successo e speriamo di rivedervi il prossimo mese: stessa ora, stesso canale!
	</p>
	</body>
</section>
</chapter>
<chapter>
<title>Gentoo Security</title>
<section>
<title>Indice</title>
<body>
     <ul>
          <li><uri link="#doc_chap2_sect1" >GLSA: pam_smb</uri></li>
          <li><uri link="#doc_chap2_sect2" >GLSA: vmware</uri></li>
          <li><uri link="#doc_chap2_sect3" >GLSA: horde</uri></li>
          <li><uri link="#doc_chap2_sect4" >GLSA: eroaster</uri></li>
          <li><uri link="#doc_chap2_sect5" >GLSA: phpwebsite</uri></li>
          <li><uri link="#doc_chap2_sect6" >GLSA: mindi</uri></li>
          <li><uri link="#doc_chap2_sect7" >GLSA: gallery</uri></li>
          <li><uri link="#doc_chap2_sect8" >GLSA: atari800</uri></li>
     </ul>
</body>
</section>

<section>
<title>GLSA: pam_smb</title>
<body>
     <p>Dall'advisory: </p>
     <p>"Se viene inserita una password lunga, si potrebbe verificare un buffer overflow che potrebbe essere sfruttato per
     eseguire codice arbitrario con i privilegi di chi invoca i servizi PAM."</p>

     <ul>
          <li>Gravità: Alta - esecuzione di codice da remoto.</li>
          <li>Versioni Vulnerabili: le precedenti a pam_smb-2.0.0_rc5</li>
          <li>Soluzione: emerge sync; emerge pam_smb; emerge clean</li>
          <li><uri link="http://marc.theaimsgroup.com/?l=gentoo-announce&amp;m=106241793528217&amp;w=2">GLSA Announcement</uri></li>
     </ul>
</body>
</section>

<section>
<title>GLSA: vmware</title>
<body>
     <p>Dall'advisory: </p>
     <p>"La GLSA 200308-03 conteneva un errore nel dire che vmware-workstation-4.0.1-5289 avrebbe corretto gli errori
     descritti nell'advisory."</p>

     <ul>
          <li>Gravità: Alta - completo accesso al pc locale.</li>
          <li>Versioni Vulnerabili: le precedenti a vmware-workstation-4.0.2.5592</li>
          <li>Soluzione: emerge sync; emerge vmware-workstation-4.0.2.5592>; emerge clean</li>
          <li><uri link="http://marc.theaimsgroup.com/?l=gentoo-announce&amp;m=106242339501516&amp;w=2">GLSA Announcement</uri></li>
     </ul>
</body>
</section>


<section>
<title>GLSA: horde</title>
<body>
     <p>Dall'advisory: </p>
     <p>"Un attaccante potrebbe spedire una email alla vittima creata in modo da forzarla a visitare un sito web. Il sito in questione
     tiene traccia di tutti gli accessi e descrive nei particolari l'origine di ogni vittima."</p>

     <ul>
          <li>Gravità: Alta - hijacking della sessione.</li>
          <li>Versioni Vulnerabili: le precedenti a horde-2.2.4_rc2</li>
          <li>Soluzione: emerge sync; emerge horde; emerge clean</li>
          <li><uri link="http://marc.theaimsgroup.com/?l=gentoo-announce&amp;m=106242613904289&amp;w=2">GLSA Announcement</uri></li>
     </ul>
</body>
</section>

<section>
<title>GLSA: eroaster</title>
<body>
     <p>Le versioni di eroaster precedenti consentivano agli utenti locali di sovrascrivere file arbitrari tramite un attacco
     symlink su un file temporaneo utilizzato come lockfile.</p>

     <ul>
          <li>Gravità: Media - attacco su symlink.</li>
          <li>Versioni Vulnerabili: le precedenti a eroaster-2.1.0-r2</li>
          <li>Soluzione: emerge sync; emerge eroaster; emerge clean</li>
          <li><uri link="http://marc.theaimsgroup.com/?l=gentoo-announce&amp;m=106249757028467&amp;w=2">GLSA Announcement</uri></li>
     </ul>
</body>
</section>

<section>
<title>GLSA: phpwebsite</title>
<body>
     <p>phpwebsite presenta una vulnerabilità sql injection nel modulo del calendario che consente ad un attaccante di eseguire queryù
     sql. Inoltre phpwebsite è anche vulnerabile a XSS, più informazioni son disponibili nell'advisory completo.</p>


     <ul>
          <li>Gravità: Alta - SQL Injection, vulnerabilità DoS e XSS.</li>
          <li>Versioni Vulnerabili: le precedenti a phpwebsite-0.9.3_p1</li>
          <li>Soluzione: emerge sync; emerge phpwebsite; emerge clean</li>
          <li><uri link="http://marc.theaimsgroup.com/?l=gentoo-announce&amp;m=106249254924303&amp;w=2">GLSA Announcement</uri></li>
     </ul>
</body>
</section>

<section>
<title>GLSA: mindi</title>
<body>
     <p>Mindi crea file in /tmp che potrebbero consentire ad un utente locale di sovrascrivere file arbitrari.</p>

     <ul>
          <li>Gravità: Media - creazione di file insicuri.</li>
          <li>Versioni Vulnerabili: le precedenti a mindi-0.86</li>
          <li>Soluzione: emerge sync; emerge mindi; emerge clean</li>
          <li><uri link="http://marc.theaimsgroup.com/?l=gentoo-announce&amp;m=106249904429698&amp;w=2">GLSA Announcement</uri></li>
     </ul>
</body>
</section>

<section>
<title>GLSA: gallery</title>
<body>
     <p>Dall'advisory: </p>
     <p>"Una vulnerabilità Cross-site scripting (XSS) in search.php di Gallery nelle versioni dalla 1.1 alla 1.3.4 consente
     ad attaccanti remoti di inserire codice arbitrario tramite il parametro searchstring."</p>

     <ul>
          <li>Gravità: Alta - cross site scripting.</li>
          <li>Versioni Vulnerabili: le precedenti a gallery-1.3.4_p1</li>
          <li>Soluzione: emerge sync; emerge gallery; emerge clean</li>
          <li><uri link="http://marc.theaimsgroup.com/?l=gentoo-announce&amp;m=106250951606667&amp;w=2">GLSA Announcement</uri></li>
     </ul>
</body>
</section>

<section>
<title>GLSA: atari800</title>
<body>
     <p>atar800 presenta un buffer overflow che potrebbe essere sfruttato da un attaccante per guadagnare privilegi di root. Sebbene in
     Gentoo il pacchetto atari800 non installi file suid root incoraggiamo gli utenti ad aggiornare il software.</p>

     <ul>
          <li>Gravità: Bassa - buffer overflow.</li>
          <li>Packages Affected: le precedenti a atari800-1.3.0-r1</li>
          <li>Rectification: emerge sync; emerge atari800; emerge clean</li>
          <li><uri link="http://marc.theaimsgroup.com/?l=gentoo-announce&amp;m=106251162709180&amp;w=2">GLSA Announcement</uri></li>
     </ul>
</body>
</section>


<section>
<title>Ultime segnalazioni di vulnerabilità</title>
<body>
     <p>
     Sono state segnalate le seguenti vulnerabilità nell'ultima settimana:
     </p>
     <ul>
          <li><uri link="http://bugs.gentoo.org/show_bug.cgi?id=27984">net-mail/exim</uri></li>
     </ul>
</body>
</section>

</chapter>
<chapter>
	<title>Racconti degli utenti</title>
	<body>
	<p>
	La rubrica è in pausa questa settimana. Ricordate di <mail link="gwn-feedback@gentoo.org">inviarci</mail> i vostri racconti
	riguardanti Gentoo in modo che le possiamo pubblicare qui.
	</p>
	</body>
</chapter>
<chapter>
<title>Lo sviluppatore della settimana</title>
<body>
<p class="secthead">Thomas Pedley</p>

<figure link="http://www.gentoo.org/images/gwn/20030908_shallax.jpg"
short="Thomas Pedley" caption="Thomas Pedley" />

<p>Lo svilulppatore di questa settimana è <mail link="shallax@gentoo.org" >Thomas
Pedley</mail> (shallax), che è l'unico responsabile per uno dei più ironici
progetti di porting di Gentoo: <uri
link="http://gentoox.shallax.com/">Gentoox</uri> (Gentoo per
XBox).  Thomas è l'unico sviluppatore ufficiale del progetto, ma lui stesso sostiene
che questo riduca il numero di conflitti tra sviluppatori. Le sue responsabilità
coprono kernel hacking, supporto agli utenti, gestione della distribuzione,
creazione di pacchetti binari, problemi legali e mantenimento del sito web.
Per coerenza, <uri link="http://gentoox.shallax.com">gentoox.shallax.com</uri> e <uri
link="http://forums.shallax.com">forums.shallax.com</uri> sono stati
recentemente migrati su un host XBox.</p>

<p>Il lavoro di Thomas è stato notato in Marzo dalla comunità di Gentoo grazie a questo
<uri link="http://forums.gentoo.org/viewtopic.php?t=44518">post</uri>
nei Forum. Nonostante altre persone fossero riuscite a far funzionare Gentoo su
XBox, Thomas è stato il primo a mettere assieme una vera e propria distribuzione
con documentazione - cosa che ha decisamente facilitato la crescita di Gentoo
sulla piattaforma ludica di Microsoft. L'idea di usare XBox come economico
PC multimediale ha aveva stuzzicato i fan di Linux per mesi. Uno dei maggiori successi
del nostro protagonista è stato di riuscire a modificare il bios Cromwell della XBox in
modo da riuscira a caricare un file initrd più grande, rendendo dunque più semplice il
boot di Gentoox. Thomas ora usa due XBox: il sempre acceso server web e un altro che
è, tragicamente, periodicamente riavviato per essere usato per giocare.</p>

<p>Oltre alle XBox, Thomas usa un desktop P4 1.8 GHz e un server Celeron 533 MHz.
Gli piace KDE, ma sulle XBox usa il più leggero WindowMaker. E' pesantemente dipendente
dai messaggi, infatti le prime cose che lancia dopo il boot sono Gaim e XChat
(o Trillian e mIRC se carica l'altro OS). Ha sentito parlare di Gentoo per la prima volta nel 2001,
ma è rimasto in una fase di 'apprendimento' fino al 2002 e ha completato la
transizione dei suoi server a Gentoo quest'anno. I suoi programmi preferiti sono
 gcc e emerge, e dice che il suo editor preferito sia pico/nano. La maggior parte del suo
 lavoro di sviluppatore è svolto con script bash, e ha deciso di implementare il suo
 sistema di patch per Gentoox (che per le XBox funziona parallelamente a portage) in bash.</p>

<p>Thomas ha da poco completato il 6th Form alla Simon Balle school, e inizierà i suoi
studi in informatica alla University of Hertfordshire tra poche settimane. Inoltre, lacora
in un supermercato locale, per raccogliere i fondi necessari all'acquisto delle sue XBox e
alla manutenzione della sua amata Peugot 205. Vive a  Hertfordshire, England, poco fuori Londra.</p>

<p>Quando gli abbiamo chiesto la sua citazione preferita, Thomas ci ha proposto un testo dei Beastie Boys:
<e>"DIY, that means do it yourself - I don't sit around waiting for
someone's help, I don't sit back and say good enough, I keep on
striving, reinventing." (DIY, che significa fallo da solo - non me ne sto ad aspettare l'aiuto di qualcun'altro,
non me ne sto fermo dicendo che tanto così va già bene, continuo a darmi da fare, a reinventare)</e>,
che sembra decisamente adatta. Ha anche osservato che "Gentoo è la distribuzione più solida che abbia mai
avuto il piacere di usare, e i suoi utenti sono gentili e desiderosi di aiutarsi a vicenda."
Ha anche voluto cogliere l'occasione di ringraziare tutti quelli che gli hanno dato una mano con il
progetto Gentoox - gli interessati sono indirizzati al README di Gentoox per prendere atto dei propri contributi.</p>

</body>
</chapter>
<chapter>
<title>Sentito nella comunità</title>
<section>
<title>Web Forum</title>
<body>
<p><b>Gentoo sul G5 e il Pegasos PPC</b></p>
<p>L'eccitazione era praticamente palpabile. Quando <uri src="http://forums.gentoo.org/profile.php?mode=viewprofile&amp;u=17436">oubipaws</uri> casualmente ha postato che ha convertito il suo nuovo Macintosh G5 a Gentoo, e riportato tempi di compilazione di meno di 15 minuti per KDE, perfino gli sviluppatori per PPC più duri sono accorsi al forum per vedere cosa stesse succedendo. Al momento la cosa è in un qualche modo non confermata, ma e se fosse davvero il primo ad avere Gentoo Linux sul nuovo cavallo di battaglia di Apple? Ad ogni modo la thread sul G5 ha praticamente seppellito la precedente buona notizia sul Pegasos PPC ora supportato, questo definitivamente e senza dubbio. Essendo uno dei pochi sviluppatori con un Pegasos G3/600 MHz a casa, <uri src="http://forums.gentoo.org/profile.php?mode=viewprofile&amp;u=26973">dholm</uri> ha Gentooificato con successo quella particolare piattaforma non-Macintosh, ma comunque basata sul PowerPC. Il prossimo LiveCD conterrà un build ufficiale, ma il kernel di dholm è pronto per essere testato da chiunque volesse provarlo. Nella stessa thread il capo-sviluppatore per PPC <uri src="http://forums.gentoo.org/profile.php?mode=viewprofile&amp;u=17163">pvdabeel</uri> ha annunciato che Gentoo girerà pure sull'AmigaOne.</p>
<ul><li><uri link="http://forums.gentoo.org/viewtopic.php?t=79513">Testing the G5, Part 1</uri></li>
<li><uri link="http://forums.gentoo.org/viewtopic.php?t=70326">Does Gentoo run on the Pegasos PPC ?</uri></li></ul>

<p><b>Fare uno tentativo</b></p>
<p>Oltre all'avere una panoramica dei forum individuali, la gente tende a cercare topic attraverso il link "posts since last visit" o stringhe di testo nel campo di ricerca rapida relativo al problema che hanno. Una delle caratteristiche meno popolari dell'interfaccia del forum phpBB è un link posto nell'angolo superiore destro della pagina che semplicemente diceOne: "View unanswered posts". Al momento ce ne sono circa 10,000, tra un sacco di immondizia c'è una grossa quantità di questioni di newbie che sono rimaste senza risposta, a volte perché il titolo non era sufficientemente chiaro, il problema troppo oscuro, o forse non molto interessante per i frequentatori del forum. Gentoomen, avete aiutato un newbie oggi? </p>
<ul><li><uri link="http://forums.gentoo.org/search.php?search_id=unanswered">View unanswered posts</uri></li></ul>
</body>
</section>
<section>
<title>gentoo-user</title>
<body>
<p>
<b>$100 UPS per Linux</b>
</p>
<p>
Per quelli che assulutamente hanno BISOGNO di far girare Gentoo, rete elettrica o meno, un uninterruptible power supply potrebbe essere esattamente ciò che state cercando. L'utente di Gentoo Chip Marshall ha iniziato la $100 Linux UPS Challenge per vedere se qualcuno era a conoscenza di UPS Linux-compatibili aquistabili per circa $100.
<uri link="http://news.gmane.org/onethread.php?group=gmane.linux.gentoo.user&amp;root=%3CNDBBLGIKBJENLAMOLFHGOENODBAB.mknecht%40controlnet.com%3E">
Leggete 
</uri> 
per tutti i grandi suggerimenti.
</p>
<p>
<b>Consigli per qpkg</b>
</p>
<p>
Vi siete mai chiesti quale ebuild ha fornito un certo file nel vostro hard drive? Questa thread della -user list ha ovverto un veloce e interessante consiglio su qpkg per fare proprio questo.
Leggetelo 
<uri link="http://news.gmane.org/onethread.php?group=gmane.linux.gentoo.user&amp;root=%3C20030901204053.8152%40balsam%3E">
qui
</uri>
.
</p>
</body>
</section>
<section>
  <title>gentoo-dev</title>
  <body>

  <p><b>Gentoo Games</b></p>
  <p>Chi ha detto che non ci sono giochi in linux? Bene, li abbiamo decisamente smentiti qui in Gentoo, con il numero di pacchetti di giochi in in app-games ora superiori a quelli in dev-perl! Dividerli un attimo dite? Bene, siete in ritardo! Mike Frysinger è un <uri link="http://article.gmane.org/gmane.linux.gentoo.devel/11855/">passo</uri> avanti a voi! Date un'occhiata per vedere dove è andata a parare la discussione.</p>

  <p><b>Portage è tuo amico</b></p>
  <p>Anche se alcuni di noi sono più che felici di semplicemente digitare emerge mioprogramma, ad alcuni in effetti fa piacere sapere come funzionano queste cose. Grant Goodyear è una di queste persone, che ha deciso che un piccolo walkthrough sarebbe stato appropriato. Date un'occhiata <uri link="http://article.gmane.org/gmane.linux.gentoo.devel/11819/">qui</uri>.
  </p>

</body>
</section>
</chapter>
<chapter>
<title>Gentoo International</title>
<body>
<p><b>Japan: Gentoo Navi Log</b></p>
<p>Mamoru Komachi, meglio conosciuto come <mail link="usata@gentoo.org">Usata</mail>, uno sviluppatore di Gentoo e mantainer del pacchetto pTeX, ha iniziato un weblog che tiene traccia dei nuovi ebuild e contiene notizie centrate attorno ai bisogni dei gentooisti giapponesi. Alcuni degli sviluppi più interessanti sono già trattati prominentemente nella sua pagina, inclusi il nuovo metodo di input giapponese im-ja di Botond Botyanszki o la nuova variante GTK2 di Sylpheed, ad esempio. Meglio di tutto: il blog è aperto alla partecipazione dell'udienza, tutti quelli che volessero aggiungere uno o l'altro coinciso pezzo di notizia a proposito di Gentoo è benvenuto di aggiungere al logbook. Guardate <uri src="http://www.smalltown.ne.jp/~usata/gentoo/">la pagina di Usata</uri> - solo se il vostro giapponese è adeguato al compito, naturalmente...</p>
</body>
</chapter>
<chapter>
<title>Portage Watch</title>
<section>
<title>I seguenti pacchetti stabili sono stati aggiornati o aggiunti a portage questa settimana:</title>
<body>
<ul>
<li>app-arch/file-roller: <uri link="http://fileroller.sourceforge.net/">manager di archivi per GNOME</uri></li>
<li>app-cdr/cdlabelgen: <uri link="http://www.aczone.com/tools/cdinsert">generatore di copertine CD, tray card </uri></li>
<li>app-crypt/gnupg: <uri link="http://www.gnupg.org/">GNU Privacy Guard, rifacimento GPL di pgp</uri></li>
<li>app-doc/abs-guide: <uri link="http://www.tldp.org/LDP/abs/html">Un tutorial sullo shell scripting in bash.</uri></li>
<li>app-doc/howto-text: <uri link="http://www.linuxdoc.org"> LDP howtos, in formato testo.</uri></li>
<li>app-editors/gedit: <uri link="http://www.gnome.org/">Editor di testo per Gnome2 desktop</uri></li>
<li>app-editors/ne: <uri link="http://ne.dsi.unimi.it/">ne nice editor, facile da usare per i principianti e potente per i maghi</uri></li>
<li>app-editors/vim: <uri link="http://www.vim.org">Vi IMproved!</uri></li>
<li>app-emacs/mew: <uri link="http://www.mew.org/">un grande MIME mail reader perr Emacs/XEmacs</uri></li>
<li>app-emacs/riece: <uri link="http://wiliki.designflaw.org/riece.cgi">Riece è un rifacimento dif Liece IRC client</uri></li>
<li>app-emacs/wl: <uri link="http://www.gohome.org/wl/index.html">a mail/news reader che supportasupporting IMAP4rev1 per emacsen</uri></li>
<li>app-emulation/epsxe: <uri link="http://www.epsxe.com/">ePSXe emulatore Playstation </uri></li>
<li>app-emulation/uae: <uri link="http://www.freiburg.linux.de/~uae/"> emulatore amiga </uri></li>
<li>app-emulation/wine: <uri link="http://www.winehq.com/">libera implementazione di Windows(tm) su Unix - CVS snapshot</uri></li>
<li>app-emulation/xmame: <uri link="http://x.mame.net/">Multiple Arcade Machine Emulator per X11</uri></li>
<li>app-emulation/xmess: <uri link="http://x.mame.net/">Multiple Arcade Machine Emulator per X11</uri></li>
<li>app-games/americas-army: <uri link="http://www.americasarmy.com/">America's Army: Operations - simulazione militare da U.S. Army per incentivare i civili a diventare soldati</uri></li>
<li>app-games/armagetron: <uri link="http://armagetron.sourceforge.net/">armagetron: 3d tron lightcycles, proprio come nel film</uri></li>
<li>app-games/asc: <uri link="http://www.asc-hq.org/">gioco di strategia a turni disegnato secondo la tradizione della serie Battle Isle</uri></li>
<li>app-games/atlas: <uri link="http://atlas.sourceforge.net/">Chart Program da usare con Flightgear Flight Simulator</uri></li>
<li>app-games/attal: <uri link="http://www.attal-thegame.org/">progetto per gioco di strategia a turni</uri></li>
<li>app-games/duke3d: <uri link="http://icculus.org/projects/duke3d/">port of the original DukeNukem 3D</uri></li>
<li>app-games/excido: <uri link="http://icculus.org/excido/">A fast paced action game</uri></li>
<li>app-games/fortune-mod: <uri link="ftp://sunsite.unc.edu/pub/Linux/games/amusements/fortune/">il noto programma fortune</uri></li>
<li>app-games/fortune-mod-bofh-excuses: <uri link="http://www.stlim.net/staticpages/index.php?page=20020814005536450">Scuse  da Bastard Operator from Hell</uri></li>
<li>app-games/fortune-mod-calvin: <uri link="http://www.netmeister.org/misc.html">Frasi da Calvin and Hobbes Comic Books</uri></li>
<li>app-games/fortune-mod-dubya: <uri link="http://dubya.seiler.us">Frasi di George W. Bush</uri></li>
<li>app-games/fortune-mod-futurama: <uri link="http://www.netmeister.org/misc.html">Frasi dall serie  TV -Futurama-</uri></li>
<li>app-games/fortune-mod-gentoo-dev: <uri link="http://oppresses.us/~avenj/index.html">Database di fortune x le frasi di #gentoo-dev</uri></li>
<li>app-games/fortune-mod-hitchhiker: <uri link="http://www.splitbrain.org/index.php?x=.%2FFortunes%2Fhitchhiker">Frasi da  Hitchhikers Guide to the Galaxy</uri></li>
<li>app-games/fortune-mod-homer: <uri link="http://www.cs.indiana.edu/~crcarter/homer/homer.html">Frasi di Homer Simpson</uri></li>
<li>app-games/fortune-mod-humorixfortunes: <uri link="http://i-want-a-website.com/about-linux/downloads.shtml">Extra fortune cookies for fortune</uri></li>
<li>app-games/fortune-mod-kernelcookies: <uri link="http://unattached.i-no.de/software-misc.shtml">Una collezione di linee divertenti dal  Linux kernel</uri></li>
<li>app-games/fortune-mod-osfortune: <uri link="http://www.dibona.com/opensources/index.shtml">Open sources fortune file</uri></li>
<li>app-games/fortune-mod-simpsons-chalkboard: <uri link="http://www.splitbrain.org/index.php?x=.%2FFortunes%2Fsimpsons">Frasi da Bart Simpson's Chalkboard, mostrate all'inzio di ogni episodio</uri></li>
<li>app-games/fortune-mod-smac: <uri link="http://homepages.ihug.com.au/~alana/">Frasi da Alpha Centauri: Alien Crossfire tech tree</uri></li>
<li>app-games/fortune-mod-sp-fortunes: <uri link="http://eol.init1.nl/pub/linux/index.php">South Park Fortunes</uri></li>
<li>app-games/fortune-mod-starwars: <uri link="http://www.splitbrain.org/index.php?x=.%2FFortunes%2Fstarwars">Frasi da StarWars, The Empire Strikes Back, and Return of the Jedi</uri></li>220
<li>app-games/fortune-mod-tao: <uri link="http://aboleo.net/software/">set of fortunes based on the Tao-Teh-Ching</uri></li>
<li>app-games/greedy: <uri link="http://www.kotinet.com/juhamattin/linux/index.html">puzzle game basato sulle ncurses</uri></li>
<li>app-games/gtetrinet: <uri link="http://gtetrinet.sourceforge.net/">clone di Tetrinet  per GNOME 2</uri></li>
<li>app-games/mirrormagic: <uri link="http://www.artsoft.org/mirrormagic/">gioco simile a Deflektor (C 64) o Mindbender (Amiga)</uri></li>
<li>app-games/monopd: <uri link="http://unixcode.org/monopd/">server per atlantik games</uri></li>
<li>app-games/nwn: <uri link="http://nwn.bioware.com/downloads/linuxclient.html">Never Winter Nights</uri></li>
<li>app-games/rocksndiamonds: <uri link="http://www.artsoft.org/rocksndiamonds/">A Boulderdash clone</uri></li>
<li>app-games/sirius: <uri link="http://sirius.bitvis.nu/">programma per giocare a otello</uri></li>
<li>app-games/spacehulk: <uri link="http://perso.enst.fr/~vinot/spacehulk/">gioco in scatola nel mondo di Warhammer 40k</uri></li>
<li>app-games/torcs: <uri link="http://torcs.org/">The Open Racing Car Simulator</uri></li>
<li>app-games/unreal-tournament: <uri link="http://www.unrealtournament.com/">Futuristic FPS</uri></li>
<li>app-games/ut2003: <uri link="http://www.unrealtournament2003.com/">Unreal Tournament 2003 - Sequel to the 1999 Game of the Year multi-player first-person shooter</uri></li>
<li>app-games/wakkabox: <uri link="http://kenn.frap.net/wakkabox/">A simple block-pushing game</uri></li>
<li>app-games/xgalaga: <uri link="http://rumsey.org/xgal.html">Clone di Galaga.</uri></li>
<li>app-i18n/freewnn: <uri link="http://www.freewnn.org/">Network-Extensible Kana-to-Kanji Conversion System</uri></li>
<li>app-i18n/kinput2: <uri link="http://www.nec.co.jp/canna/">Input serve giapponese che supporta il protocollo XIM</uri></li>
<li>app-i18n/scim: <uri link="http://www.turbolinux.com.cn/~suzhe/scim/">Smart Common Input Method (SCIM) is a Input Method (IM) development platform</uri></li>
<li>app-i18n/scim-chinese: <uri link="http://www.turbolinux.com.cn/~suzhe/scim/">Smart Common Input Method (SCIM) Closed Source Pinyin Input Method</uri></li>
<li>app-i18n/skk-jisyo-extra: <uri link="http://openlab.ring.gr.jp/skk/dic.html">Extra SKK dictionaries in plain text and cdb format</uri></li>
<li>app-i18n/uim: <uri link="http://anthy.sourceforge.jp/">UIM is a simple, secure and flexible input method library</uri></li>
<li>app-misc/kdirstat: <uri link="http://kdirstat.sourceforge.net/">KDirStat - nice KDE replacement to du command</uri></li>
<li>app-misc/magicpoint: <uri link="http://www.mew.org/mgp/">an X11 based presentation tool</uri></li>
<li>app-misc/welcome2l: <uri link="http://www.littleigloo.org/"> Welcome to Linux, ANSI login logo for Linux</uri></li>
<li>app-misc/xosview: <uri link="http://xosview.sourceforge.net">X11 operating system viewer</uri></li>
<li>app-office/mdbtools: <uri link="http://sourceforge.net/projects/mdbtools/">A set of libraries and utilities for reading Microsoft Access database (MDB) files</uri></li>
<li>app-office/scribus: <uri link="http://web2.altmuehlnet.de/fschmid/">Desktop Publishing (DTP) and Layout program for Linux.</uri></li>
<li>app-sci/bioperl: <uri link="http://www.bioperl.org/">collection of tools for bioinformatics, genomics and life science research</uri></li>
<li>app-sci/ksimus: <uri link="http://ksimus.berlios.de/">KSimus is a KDE tool for simulation, automatization and visualization of technical processes.</uri></li>
<li>app-sci/octave: <uri link="http://www.octave.org/">GNU Octave is a high-level language (MatLab compatible) intended for numerical computations</uri></li>
<li>app-sci/octave-forge: <uri link="http://octave.sourceforge.net/">A collection of custom scripts, functions and extensions for GNU Octave</uri></li>
<li>app-text/epstool: <uri link="http://www.cs.wisc.edu/~ghost/gsview/epstool.htm">Creates or extracts preview images in EPS files, fixes bounding boxes,converts to bitmaps.</uri></li>
<li>app-text/htmldoc: <uri link="http://www.easysw.com/htmldoc/">Convert HTML pages into a PDF document</uri></li>
<li>app-text/tkinfo: <uri link="http://math-www.uni-paderborn.de/~axel/tkinfo/">Info Browser in TK</uri></li>
<li>app-text/uudeview: <uri link="http://www.fpx.de/fp/Software/UUDeview/">uu, xx, base64, binhex decoder</uri></li>
<li>dev-cpp/gtkmm: <uri link="http://gtkmm.sourceforge.net/">C++ interface for GTK+2</uri></li>
<li>dev-db/mysql: <uri link="http://www.mysql.com/">A fast, multi-threaded, multi-user SQL database server</uri></li>
<li>dev-db/tora: <uri link="http://www.globecom.se/tora/">TOra - Toolkit For Oracle</uri></li>
<li>dev-dotnet/mono: <uri link="http://www.go-mono.com/">Mono runtime and class librarier, a C# compiler/interpreter</uri></li>
<li>dev-dotnet/pnet: <uri link="http://www.dotgnu.org/">Portable .NET runtime, compiler, tools</uri></li>
<li>dev-games/crystalspace: <uri link="http://crystal.sourceforge.net/">portable 3D Game Development Kit written in C++</uri></li>
<li>dev-games/crystalspace-cvs: <uri link="http://crystal.sourceforge.net/">portable 3D Game Development Kit written in C++</uri></li>
<li>dev-java/infobus: <uri link="http://java.sun.com/products/javabeans/infobus/index.html">InfoBus enables dynamic exchange of data between JavaBeans component architecture.</uri></li>
<li>dev-java/jad: <uri link="http://kpdus.tripod.com/jad.html">Jad - the fast JAva Decompiler</uri></li>
<li>dev-java/jaf: <uri link="http://java.sun.com/products/javabeans/glasgow/jaf.html">Sun's JavaBeans Activation Framework (JAF)</uri></li>
<li>dev-java/java-config: <uri link="http://www.gentoo.org/">Utility to change the Java Virtual Machine being used</uri></li>
<li>dev-java/java-sdk-docs: <uri link="http://java.sun.com/j2se/1.3/docs.html">Javadoc for Java SDK version 1.3.1</uri></li>
<li>dev-java/javamail: <uri link="http://java.sun.com/products/javamail/index.html">A Java-based framework to build multiplatform mail and messaging applications.</uri></li>
<li>dev-java/jdbc2-oracle: <uri link="http://otn.oracle.com/software/tech/java/sqlj_jdbc/htdocs/jdbc817.html">JDBC Drivers for Oracle</uri></li>
<li>dev-java/jdbc3-oracle: <uri link="http://otn.oracle.com/software/tech/java/sqlj_jdbc/htdocs/jdbc9201.html">JDBC 3.0 Drivers for Oracle</uri></li>
<li>dev-java/jmf: <uri link="http://java.sun.com/products/java-media/jmf/">The Java Media Framework API (JMF) enables audio, video and other time-based media to be added to Java applications and applets.</uri></li>
<li>dev-java/jrockit: <uri link="http://commerce.bea.com/downloads/weblogic_jrockit.jsp">BEA WebLogic's J2SE Development Kit, version 8.1</uri></li>
<li>dev-java/jython: <uri link="http://www.jython.org">Java Python implementation</uri></li>
<li>dev-java/sun-jdk: <uri link="http://java.sun.com/j2se/1.4.2/download.html">Sun's J2SE Development Kit, version 1.4.2</uri></li>
<li>dev-lang/tolua: <uri link="http://www.tecgraf.puc-rio.br/~celes/tolua/">a tool that simplifies the integration of C/C++ code with Lua</uri></li>
<li>dev-libs/atk: <uri link="http://developer.gnome.org/projects/gap/">Gnome Accessibility Toolkit</uri></li>
<li>dev-libs/boost: <uri link="http://www.boost.org">Boost provides free peer-reviewed portable C++ source libraries.</uri></li>
<li>dev-libs/elfutils: <uri link="http://www.redhat.com/">Libraries and utilities to handle compiled objects.</uri></li>
<li>dev-libs/hdf5: <uri link="http://hdf.ncsa.uiuc.edu/HDF5/">HDF5 is a general purpose library and file format for storing scientific data.</uri></li>
<li>dev-libs/libxslt: <uri link="http://www.xmlsoft.org/">XSLT libraries and tools</uri></li>
<li>dev-libs/qsa: <uri link="http://www.trolltech.com/">QSA</uri></li>
<li>dev-perl/DB_File: <uri link="http://www.cpan.org/modules/by-module/DB_File/${P}.readme">A Berkeley DB Support Perl Module</uri></li>
<li>dev-perl/Net-SNMP: <uri link="http://www.cpan.org/modules/by-module/Net/${P}.readme">A SNMP Perl Module</uri></li>
<li>dev-php/mod_php: Apache module for PHP</li>
<li>dev-python/4Suite: <uri link="http://www.4suite.org/">Python tools for XML processing and object-databases.</uri></li>
<li>dev-python/gnome-python: <uri link="http://www.daa.com.au/~james/gnome/">gnome-python</uri></li>
<li>dev-python/pygtk: <uri link="http://www.daa.com.au/~james/pygtk/">GTK+2 bindings for Python</uri></li>
<li>dev-python/pykde: <uri link="http://www.riverbankcomputing.co.uk/pykde/">set of Python bindings for the KDE libs</uri></li>
<li>dev-python/pyorbit: <uri link="http://www.daa.com.au/~james/pygtk/">ORBit2 bindings for Python</uri></li>
<li>dev-python/pyxml: <uri link="http://pyxml.sourceforge.net/">A collection of libraries to process XML with Python.</uri></li>
<li>dev-util/guile: <uri link="http://www.gnu.org/software/guile/">Scheme interpreter</uri></li>
<li>gnome-base/ORBit2: <uri link="http://www.gnome.org/">ORBit2 is a high-performance CORBA ORB</uri></li>
<li>gnome-base/bonobo-activation: <uri link="http://www.gnome.org/">Gnome2 replacement for OAF</uri></li>
<li>gnome-base/gconf: <uri link="http://www.gnome.org/">Gnome Configuration System and Daemon</uri></li>
<li>gnome-base/gdm: <uri link="http://www.gnome.org/">GNOME2 Display Manager</uri></li>
<li>gnome-base/gnome: <uri link="http://www.gnome.org/">Meta package for the GNOME desktop.</uri></li>
<li>gnome-base/gnome-applets: <uri link="http://www.gnome.org/">Applets for the Gnome2 Desktop and Panel</uri></li>
<li>gnome-base/gnome-desktop: <uri link="http://www.gnome.org/">Libraries for the gnome desktop that is not part of the UI</uri></li>
<li>gnome-base/gnome-mime-data: <uri link="http://www.gnome.org/">MIME database for Gnome</uri></li>
<li>gnome-base/gnome-panel: <uri link="http://www.gnome.org/">The Panel for Gnome2</uri></li>
<li>gnome-base/gnome-session: <uri link="http://www.gnome.org/">the Gnome2 session manager</uri></li>
<li>gnome-base/gnome-vfs: <uri link="http://www.gnome.org/">Gnome Virtual Filesystem</uri></li>
<li>gnome-base/libbonobo: <uri link="http://www.gnome.org/">The GNOME CORBA framework</uri></li>
<li>gnome-base/libbonoboui: <uri link="http://www.gnome.org/">User Interface part of Lib bonobo</uri></li>
<li>gnome-base/libglade: <uri link="http://www.gnome.org/">GLADE is a interface builder</uri></li>
<li>gnome-base/libgnome: <uri link="http://www.gnome.org/">Essential Gnome Libraries</uri></li>
<li>gnome-base/libgnomecanvas: <uri link="http://www.gnome.org/">the Gnome 2 Canvas library</uri></li>
<li>gnome-base/libgnomeprint: <uri link="http://www.gnome.org/">Printer handling for Gnome</uri></li>
<li>gnome-base/libgnomeprintui: <uri link="http://www.gnome.org/">user interface libraries for gnome print</uri></li>
<li>gnome-base/libgnomeui: <uri link="http://www.gnome.org/">User interface part of libgnome</uri></li>
<li>gnome-base/libgtop: <uri link="http://www.gnome.org/">library that proivdes top functionality to applications</uri> </li>
<li>gnome-base/librsvg: <uri link="http://www.gnome.org/">rendering svg library</uri></li>
<li>gnome-base/nautilus: <uri link="http://www.gnome.org/projects/nautilus/">A filemanager for the Gnome2 desktop</uri></li>
<li>gnome-extra/acme: <uri link="http://www.hadess.net/misc-code.php3">GNOME tool to make use of the multimedia buttons present on most laptops and internet keyboards.</uri></li>
<li>gnome-extra/gnome-games: <uri link="http://www.gnome.org/">Games for the GNOME desktop</uri></li>
<li>gnome-extra/gnome-media: <uri link="http://www.prettypeople.org/~iain/gnome-media/">Multimedia related programs for the Gnome2 desktop</uri></li>
<li>gnome-extra/gnome-system-monitor: <uri link="http://www.gnome.org/">Gnome System Monitor</uri></li>
<li>gnome-extra/yelp: <uri link="http://www.gnome.org/">Help browser for Gnome2</uri></li>
<li>kde-base/kdeadmin: KDE administration tools (user manager, etc.)</li>
<li>media-fonts/artwiz-fonts: <uri link="http://fluxbox.sourceforge.net/docs/artwiz-fonts.php">Artwiz Fonts</uri></li>
<li>media-fonts/kochi-substitute: <uri link="http://efont.sourceforge.jp/">Kochi Japanese TrueType fonts with Wadalab Fonts</uri>	einfo "${HOMEPAGE} for details."</li>
<li>media-fonts/mikachan-font: <uri link="http://mikachan-font.com/">Mikachan Japanese TrueType fonts</uri></li>
<li>media-fonts/mplus-fonts: <uri link="http://mplus-fonts.sourceforge.jp/">mplus Japanese BDF FONTS</uri></li>
<li>media-fonts/shinonome: <uri link="http://openlab.jp/efont/shinonome/">Japanese bitmap fonts for X</uri></li>
<li>media-gfx/eog: <uri link="http://www.gnome.org/">the Eye Of Gnome - Image Viewer and Cataloger for Gnome2</uri></li>
<li>media-gfx/gliv: <uri link="http://gliv.tuxfamily.org">An image viewer that uses OpenGL</uri></li>
<li>media-gfx/gnuplot: <uri link="http://www.gnuplot.info">Quick and useful plotting program</uri></li>
<li>media-gfx/gphoto2: <uri link="http://www.gphoto.org/">free, redistributable digital camera software application</uri></li>
<li>media-gfx/qiv: <uri link="http://www.klografx.net/qiv/">Quick Image Viewer</uri></li>
<li>media-gfx/sane-frontends: <uri link="http://www.mostang.com/sane/">Scanner Access Now Easy</uri></li>
<li>media-libs/fontconfig: <uri link="http://fontconfig.org/">A library for configuring and customizing font access.</uri></li>
<li>media-libs/gst-plugins: <uri link="http://gstreamer.sourceforge.net">Additional plugins for gstreamer - streaming media framework</uri></li>
<li>media-libs/gstreamer: <uri link="http://gstreamer.sourceforge.net">Streaming media framework</uri></li>
<li>media-libs/imlib2: <uri link="http://www.enlightenment.org/pages/imlib2.html">Version 2 of an advanced replacement library for libraries like libXpm</uri></li>
<li>media-libs/libemf: <uri link="http://libemf.sourceforge.net/">Library implementation of ECMA-234 API for the generation of enhanced metafiles.</uri></li>
<li>media-libs/netpbm: <uri link="http://netpbm.sourceforge.net/">A set of utilities for converting to/from the netpbm (and related) formats</uri></li>
<li>media-libs/xine-lib: <uri link="http://xine.sourceforge.net/">Core libraries for Xine movie player</uri></li>
<li>media-plugins/xmms-crossfade: <uri link="http://www.netcologne.de/~nc-eisenlpe2/xmms-crossfade/">XMMS Plugin for crossfading, and continuous output.</uri></li>
<li>media-sound/freqtweak: <uri link="http://freqtweak.sourceforge.net">tool for FFT-based realtime audio spectral manipulation and display</uri></li>
<li>media-sound/gnomeradio: <uri link="http://mfcn.ilo.de/gnomeradio/">A GNOME2 radio tuner</uri></li>
<li>media-sound/streamripper: <uri link="http://streamripper.sourceforge.net/">Extracts and records individual MP3 file tracks from shoutcast streams</uri></li>
<li>media-tv/nxtvepg: <uri link="http://nxtvepg.sourceforge.net/">receive and browse free TV programme listings via bttv for tv networks in Europe</uri></li>
<li>media-video/cinelerra: <uri link="http://heroinewarrior.com/cinelerra.php3">Cinelerra - Professional Video Editor</uri></li>
<li>media-video/mjpegtools: <uri link="http://mjpeg.sourceforge.net/">Tools for MJPEG video</uri></li>
<li>media-video/mplayer: <uri link="http://www.mplayerhq.hu/">Media Player for Linux</uri></li>
<li>media-video/transcode: <uri link="http://zebra.fh-weingarten.de/~transcode/">video stream processing tool</uri></li>
<li>media-video/xvattr: <uri link="http://www.dtek.chalmers.se/groups/dvd/">X11 XVideo Querying/Setting Tool from Ogle project</uri></li>
<li>net-analyzer/libnasl: <uri link="http://www.nessus.org/">A remote security scanner for Linux (libnasl)</uri></li>
<li>net-analyzer/nessus: <uri link="http://www.nessus.org/">A remote security scanner for Linux</uri></li>
<li>net-analyzer/nessus-core: <uri link="http://www.nessus.org/">A remote security scanner for Linux (nessus-core)</uri></li>
<li>net-analyzer/nessus-libraries: <uri link="http://www.nessus.org/">A remote security scanner for Linux (nessus-libraries)</uri></li>
<li>net-analyzer/nessus-plugins: <uri link="http://www.nessus.org/">A remote security scanner for Linux (nessus-plugins)</uri></li>
<li>net-analyzer/nmap: <uri link="http://www.insecure.org/nmap/">utility for network exploration or security auditing</uri></li>
<li>net-analyzer/snort: <uri link="http://www.snort.org/">Libpcap-based packet sniffer/logger/lightweight IDS</uri></li>
<li>net-dialup/capi4k-utils: <uri link="ftp://ftp.in-berlin.de/pub/capi4linux/">Capi4Linux Utils</uri></li>
<li>net-dialup/pptpclient: <uri link="http://pptpclient.sourceforge.net/">Linux client for PPTP</uri></li>
<li>net-firewall/shorewall: <uri link="http://www.shorewall.net">Full state iptables firewall</uri></li>
<li>net-fs/ftpfs: <uri link="http://ftpfs.sourceforge.net/">A filesystem for mounting FTP volumes</uri></li>
<li>net-im/centericq: <uri link="http://konst.org.ua/eng/software/centericq/info.html">A ncurses ICQ/Yahoo!/MSN/IRC/Jabber Client</uri></li>
<li>net-im/imcom: <uri link="http://imcom.floobin.cx">Python commandline Jabber Client</uri></li>
<li>net-im/licq: <uri link="http://www.licq.org/">ICQ Client with v8 support</uri> </li>
<li>net-im/msnlib: <uri link="http://auriga.wearlab.de/~alb/msnlib">A Python MSN messenger protocol library and client</uri></li>
<li>net-libs/linc: <uri link="http://www.gnome.org/">A library to ease the writing of networked applications</uri></li>
<li>net-mail/evolution: <uri link="http://www.ximian.com">A GNOME groupware application, a Microsoft Outlook workalike</uri></li>
<li>net-mail/f-prot: <uri link="http://www.f-prot.com/">Frisk Software's f-prot virus scanner</uri></li>
<li>net-mail/queue-fix: <uri link="http://www.netmeridian.com/e-huss/">Qmail Queue Repair Application with support for big-todo</uri></li>
<li>net-misc/atftp: <uri link="ftp://ftp.mamalinux.com/pub/atftp/">Advanced TFTP implementation client/server</uri></li>
<li>net-misc/gyach: <uri link="http://www4.infi.net/~cpinkham/gyach/">GTK+-based Yahoo! chat client</uri></li>
<li>net-misc/ltsp-core: <uri link="http://www.ltsp.org/">LTSP - Linux Terminal Server Project</uri></li>
<li>net-misc/pxes: PXES is a package for building thin clients using multiple types of clients</li>
<li>net-misc/rsync: <uri link="http://rsync.samba.org/">File transfer program to keep remote files into sync</uri></li>
<li>net-misc/telnet-bsd: <uri link="ftp://ftp.suse.com/pub/people/kukuk/ipv6/">Telnet and telnetd ported from OpenBSD with IPv6 support</uri></li>
<li>net-misc/tftp-hpa: <uri link="http://www.kernel.org/pub/software/network/tftp/">port of the OpenBSD TFTP server</uri></li>
<li>net-misc/whois: <uri link="http://www.linux.it/~md/software/">improved Whois Client</uri></li>
<li>net-p2p/gnunet: <uri link="http://www.ovmj.org/GNUnet/">GNUnet is an anonymous, distributed, reputation based network.</uri></li>
<li>net-p2p/xmule: <uri link="http://www.xmule.org/">wxWindows based client for the eDonkey/eMule/lMule network</uri></li>
<li>net-www/apache: <uri link="http://www.apache.org http://www.modssl.org">The Apache Web Server</uri></li>
<li>net-www/mozilla-firebird: <uri link="http://www.mozilla.org/projects/firebird/">The Mozilla Firebird Web Browser</uri></li>
<li>net-www/opera: <uri link="http://www.opera.com/linux/">Opera web browser.</uri></li>
<li>net-www/straw: <uri link="http://www.nongnu.org/straw/">rss news aggregator</uri></li>
<li>sys-apps/checkpolicy: <uri link="http://www.nsa.gov/selinux">SELinux policy compiler</uri></li>
<li>sys-apps/cloop: <uri link="http://www.knopper.net/knoppix/">Compressed filesystem loopback kernel module</uri></li>
<li>sys-apps/coreutils: <uri link="http://www.gnu.org/software/coreutils/">Standard GNU utility per file (chmod, cp, dd, dir, ls...), utility per testi(sort, tr, head, wc..), e utility shell (whoami, who,...)</uri></li>
<li>sys-apps/dd_rescue: <uri link="http://www.garloff.de/kurt/linux/ddrescue/">simile  a dd ma può copiare da una sorgente con errori</uri></li>
<li>sys-apps/debianutils: <uri link="http://packages.debian.org/unstable/base/debianutils.html">selezione di tool da debian</uri></li>
<li>sys-apps/hdparm: <uri link="http://www.ibiblio.org/pub/Linux/system/hardware/">Utility per cambiare i parametri degli hard disk</uri></li>
<li>sys-apps/policycoreutils: <uri link="http://www.nsa.gov/selinux">SELinux core utilites</uri></li>
<li>sys-apps/portage: <uri link="http://www.gentoo.org">Portage ports system</uri></li>
<li>sys-apps/smartmontools: <uri link="http://smartmontools.sourceforge.net/">control and monitor storage systems using the Self-Monitoring, Analysis and Reporting Technology System (S.M.A.R.T.)</uri></li>
<li>sys-apps/xinetd: <uri link="http://www.xinetd.org">Xinetd is a powerful replacement for inetd, with advanced features</uri></li>
<li>sys-apps/xmbmon: <uri link="http://www.nt.phys.kyushu-u.ac.jp/shimizu/download/download.html">Mother Board Monitor Program per X Window System</uri></li>
<li>sys-cluster/cppvm: <uri link="http://www.informatik.uni-stuttgart.de/ipvr/bv/cppvm/index.html">CPPVM: A C++ Interface to PVM</uri></li>
<li>sys-cluster/pvm: <uri link="http://www.epm.ornl.gov/pvm/pvm_home.html">PVM: Parallel Virtual Machine</uri></li>
<li>sys-devel/binutils: <uri link="http://sources.redhat.com/binutils/">Tool necessari per compilare programmi</uri></li>
<li>sys-devel/distcc: <uri link="http://distcc.samba.org/">programma per distribuire la compilazione di codice C su diverse macchine in una rete</uri></li>
<li>sys-devel/gcc: <uri link="http://www.gnu.org/software/gcc/gcc.html">The GNU Compiler Collection.  Include i compilatori C/C++ e java</uri></li>
<li>sys-devel/hardened-gcc: <uri link="http://www.gentoo.org/proj/en/hardened/etdyn-ssp.xml">transparent gcc compiler change for PaX/etdyn ASLR w/ propolice/SSP</uri></li>
<li>sys-devel/prelink: <uri link="ftp://people.redhat.com/jakub/prelink">eseguibili modificati in modo che le librerie dinamiche carichino + velocemnte</uri></li>
<li>sys-kernel/mips-headers: <uri link="http://www.linux-mips.org/"> Linux-Mips CVS headers per macchine MIPS-based</uri></li>
<li>sys-kernel/mm-sources: Sorgenti completi per il kernel in svilupo con le patch di Andrew Morton</li>
<li>sys-kernel/vanilla-sources: <uri link="http://www.kernel.org/">Sorgenti completi per il Gentoo Linux kernel</uri></li>
<li>x11-base/xfree: <uri link="http://www.xfree.org">Xfree86: X server famoso e libero</uri></li>
<li>x11-libs/gtk+: <uri link="http://www.gtk.org/">Gimp ToolKit +</uri></li>
<li>x11-libs/libwnck: <uri link="http://www.gnome.org/">A window navigation construction kit</uri></li>
<li>x11-libs/pango: <uri link="http://www.pango.org/">Text rendering and Layout library</uri></li>
<li>x11-libs/qt: <uri link="http://www.trolltech.com/">QT</uri></li>
<li>x11-misc/icebgset: <uri link="http://icecc.sourceforge.net/">IceWM background editor</uri></li>
<li>x11-misc/icets: <uri link="http://icecc.sourceforge.net/">IceWM Theme Editor</uri></li>
<li>x11-misc/icewm-tools: <uri link="http://icecc.sourceforge.net/">Convenience package for IceWM control center and tools</uri></li>
<li>x11-misc/shared-mime-info: <uri link="http://www.freedesktop.org">The Shared MIME-info Database specification.</uri></li>
<li>x11-misc/superkaramba: <uri link="http://netdragon.sourceforge.net/">Una versione di Karamba con estensioni built-in</uri></li>
<li>x11-misc/x2vnc: <uri link="http://www.hubbe.net/~hubbe/x2vnc.html">Controlla un computer remoto che esgue VNC da X</uri></li>
<li>x11-misc/xnview: <uri link="http://www.xnview.com/">XnView image viewer/converter</uri></li>
<li>x11-plugins/wmclockmon: <uri link="http://tnemeth.free.fr/projets/dockapps.html">orologio digitale con tre differenti stili.</uri></li>
<li>x11-terms/gnome-terminal: <uri link="http://www.gnome.org/">Gnome Terminal</uri></li>
<li>x11-themes/gnome-icon-theme: <uri link="http://www.gnome.org/">tema di icone di default x Gnome2 </uri></li>
<li>x11-themes/gnome-themes: <uri link="http://www.gnome.org/softwaremap/projects/gnome-themes">A set of gnome2 themes, with sets for users with limited or low vision</uri></li>
<li>x11-themes/gtk-engines: Theme Engines from GNOME including Pixmap, Metal, Raleigh, Redmond95, Raleigh and Notif</li>
<li>x11-themes/mandrake-artwork: <uri link="http://www.mandrakelinux.com">Mandrake's Galaxy theme for GTK1, GTK2, Metacity and KDE</uri></li>
<li>x11-themes/thinkeramik: <uri link="http://kde-look.org/content/show.php?content=6986">uno stile di  kde modificato da keramik</uri></li>
<li>x11-wm/fluxspace: <uri link="http://fluxspace.sourceforge.net/">Enhancements for workspace management within Fluxbox.</uri></li>
<li>x11-wm/metacity: <uri link="http://www.gnome.org/softwaremap/projects/metacity/">piccolo  WindowManager in gtk2</uri></li>
</ul>
<p>Categorie totali: 96</p>
<p>Pacchetti totali: 5558</p>
</body>
</section>
</chapter>
<chapter>
<title>Bugzilla</title>
<section>
<title>Sommario</title>
<body>
     <ul>
          <li><uri link="#doc_chap1_sect2" >Statistiche</uri></li>
          <li><uri link="#doc_chap1_sect3" >Classifica dei bug chiusi</uri></li>
	  <li><uri link="#doc_chap1_sect4" >Classifica dei nuovi bug</uri></li>
     </ul>
</body>
</section>

<section>
<title>Statistics</title>
<body>
<p>
      La comunità Gentoo usa Bugzilla (<uri link="http://bugs.gentoo.org" >bugs.gentoo.org</uri>) per annotare e tenere traccia di bugs
     notifiche, suggerimenti e altre interazioni con il team di sviluppo.Tra il 29 Agosto 2003 e il 04 Settembre 2003, l'attività
     sul sito è stata:
     </p>
     <ul>
          <li>384 nuovi bug durante questo periodo</li>
	  <li>182 bug chiusi durante questo periodo</li>
	  <li>8 bug precedentemente chiusi sono stati riaperti</li>
     </ul>
     <p>
     Degli attuali 3837 bug aperti: 94 sono classificati come 'bloccanti', 196 sono classificati come 'critici', e  287 sono classificiati come 'primari'.
     </p>
</body>
</section>

<section>
<title>Classifica dei bug chiusi</title>
<body>
     <p>
    Gli sviluppatori e i team che hanno chiuso il maggior numero di bug durante questo periodo:
     </p>
     <ul>
<li><mail link="liquidx@gentoo.org" >Alastair Tse</mail>, con 20
              <uri link="http://bugs.gentoo.org/buglist.cgi?bug_status=RESOLVED&amp;bug_status=CLOSED&amp;chfield=bug_status&amp;chfieldfrom=2003-08-29&amp;chfieldto=2003-09-04&amp;resolution=FIXED&amp;assigned_to=liquidx@gentoo.org" >bug chiusi</uri>
            </li>
<li><mail link="games@gentoo.org" >Gentoo Games</mail>, con 15
              <uri link="http://bugs.gentoo.org/buglist.cgi?bug_status=RESOLVED&amp;bug_status=CLOSED&amp;chfield=bug_status&amp;chfieldfrom=2003-08-29&amp;chfieldto=2003-09-04&amp;resolution=FIXED&amp;assigned_to=games@gentoo.org" >bug chiusi</uri>
            </li>
<li><mail link="x86-kernel@gentoo.org" >x86 Kernel Team</mail>, con 8
              <uri link="http://bugs.gentoo.org/buglist.cgi?bug_status=RESOLVED&amp;bug_status=CLOSED&amp;chfield=bug_status&amp;chfieldfrom=2003-08-29&amp;chfieldto=2003-09-04&amp;resolution=FIXED&amp;assigned_to=x86-kernel@gentoo.org" >bug chiusi</uri>
            </li>
<li><mail link="security@gentoo.org" >Gentoo Security</mail>, con 8
              <uri link="http://bugs.gentoo.org/buglist.cgi?bug_status=RESOLVED&amp;bug_status=CLOSED&amp;chfield=bug_status&amp;chfieldfrom=2003-08-29&amp;chfieldto=2003-09-04&amp;resolution=FIXED&amp;assigned_to=security@gentoo.org" >bug chiusi</uri>
            </li>
<li><mail link="phosphan@gentoo.org" >Patrick Kursawe</mail>, con 8
              <uri link="http://bugs.gentoo.org/buglist.cgi?bug_status=RESOLVED&amp;bug_status=CLOSED&amp;chfield=bug_status&amp;chfieldfrom=2003-08-29&amp;chfieldto=2003-09-04&amp;resolution=FIXED&amp;assigned_to=phosphan@gentoo.org" >bug chiusi</uri>
            </li>
<li><mail link="gnome@gentoo.org" >Gnome Desktop Team</mail>, con 8
              <uri link="http://bugs.gentoo.org/buglist.cgi?bug_status=RESOLVED&amp;bug_status=CLOSED&amp;chfield=bug_status&amp;chfieldfrom=2003-08-29&amp;chfieldto=2003-09-04&amp;resolution=FIXED&amp;assigned_to=gnome@gentoo.org" >bug chiusi</uri>
            </li>
</ul>
</body>
</section>

<section>
<title>Classifica dei nuovi bug</title>
<body>
     <p>
     Gli sviluppatori e i team a cui sono stati assegnati il maggior numero di nuovi bug durante questo periodo sono:
     </p>
     <ul>
<li><mail link="sound@gentoo.org" >Gentoo Sound Team</mail>, con 19
              <uri link="http://bugs.gentoo.org/buglist.cgi?bug_status=NEW&amp;bug_status=ASSIGNED&amp;bug_status=REOPENED&amp;chfield=assigned_to&amp;chfieldfrom=2003-08-29&amp;chfieldto=2003-09-04&amp;assigned_to=sound@gentoo.org" >nuovi bug</uri>
            </li>
<li><mail link="web-apps@gentoo.org" >Gentoo Web Application Packages Maintainers</mail>, con 18
              <uri link="http://bugs.gentoo.org/buglist.cgi?bug_status=NEW&amp;bug_status=ASSIGNED&amp;bug_status=REOPENED&amp;chfield=assigned_to&amp;chfieldfrom=2003-08-29&amp;chfieldto=2003-09-04&amp;assigned_to=web-apps@gentoo.org" >nuovi bug</uri>
            </li>
<li><mail link="azarah@gentoo.org" >Martin Schlemmer</mail>, con 12
              <uri link="http://bugs.gentoo.org/buglist.cgi?bug_status=NEW&amp;bug_status=ASSIGNED&amp;bug_status=REOPENED&amp;chfield=assigned_to&amp;chfieldfrom=2003-08-29&amp;chfieldto=2003-09-04&amp;assigned_to=azarah@gentoo.org" >nuovi bug</uri>
            </li>
<li><mail link="python@gentoo.org" >Python Gentoo Team</mail>, con 9
              <uri link="http://bugs.gentoo.org/buglist.cgi?bug_status=NEW&amp;bug_status=ASSIGNED&amp;bug_status=REOPENED&amp;chfield=assigned_to&amp;chfieldfrom=2003-08-29&amp;chfieldto=2003-09-04&amp;assigned_to=python@gentoo.org" >nuovi bug</uri>
            </li>
<li><mail link="media-tv@gentoo.org" >Media-TV Team</mail>, con 9
              <uri link="http://bugs.gentoo.org/buglist.cgi?bug_status=NEW&amp;bug_status=ASSIGNED&amp;bug_status=REOPENED&amp;chfield=assigned_to&amp;chfieldfrom=2003-08-29&amp;chfieldto=2003-09-04&amp;assigned_to=media-tv@gentoo.org" >nuovi bug</uri>
            </li>
</ul>
</body>
</section>
</chapter>
<chapter>
<title>Tips and Tricks</title>
  
<body>

  <p class="secthead">Usare SSH comandi remoti</p>

  <p>
    Il trucco di questa settimana vi mostra un'uso poco comune di SSH. Molte persone usano SSH per eseguire il login
    su un server o una box remota. Comunque, potete anche usare SSH per dare comandi remoti
    a un server aprire una shell di login.
  </p>
  <note>
    Per usare SSH senza inserirela password tutte le volte, usate <uri
      link="http://www.gentoo.org/proj/en/keychain.xml">Keychain</uri>.
  </note>

  <p>
    Per dare comandi tramite SSH, semplicemnte digitate il comando dopo le normali 
    informazioni di login di SSH (esempio <c>ssh user@host command</c>). Il seguente
    esempio vi mostra come vedere i file di log su un server web remoto.
  </p>

  <pre caption="Guardare gli access log di Apache2">
% <i>ssh david@www.example.com tail /var/log/apache2/access_log</i>
  </pre>

  <p>
    In alternativa, potete cambiare la password tramite SSH (sebbene sia meglio
    usare l'autenticazione via chiave con SSH invece delle password).
  </p>

  <pre caption="Cambiare password da remoto">
% <i>ssh david@example.com passwd</i>
(current) UNIX password: <i>password</i>
New UNIX password: <i>new_password</i>
Retype new UNIX password: <i>new_password</i>
Changing password for david
  </pre>

  <p>
    Questo dovrebbe farvi eseguire comandi remoti con SSH. Gardate la pagina man di SSH
    per maggiori opzioni.
  </p>

</body>
</chapter>

<chapter>
<title>Firma della settimana</title>
<body>
<p>
La firma della settimana è in pausa questa settimana.
</p>
</body>
</chapter>
<chapter>
<title>Partenze, Arrivi e cambiamenti</title>
	<section>
		<title>Partenze</title>
		<body>
		<p>I seguenti sviluppatori hanno recentemente lasciato il Gentoo team:
			<ul>
				<li><e>nessuno questa settimana</e></li>
			</ul>
		</p>
		</body>
	</section>
	<section>
		<title>Arrivi</title>
		<body>
		<p>I seguenti sviluppatori si sono recentemente uniti al Gentoo Linux team:</p>
		<ul>
				<li><e>nessuno questa settimana</e></li>
		</ul>
		</body>
	</section>
	<section>
		<title>Cambiamenti</title>
		<body>
		<p>I seguenti sviluppatori hanno recentemente cambiato ruolo all'interno del progetto Gentoo Linux.</p>
			<ul>
				<li><e>nessuno questa settimana</e></li>
			</ul>
		</body>
	</section>
</chapter>
<chapter>
<title>Contribuite alla GWN</title>
	<body>
	<p>Vi interessa contribuire alla Gentoo Weekly Newsletter? Mandateci una <mail link="gwn-feedback@gentoo.org">email</mail>.</p>
	</body>
</chapter>
<chapter>
	<title>Commenti alla GWN</title>
	<body>
	<p>Mandateci i vostri <mail link="gwn-feedback@gentoo.org">commenti</mail>e aiutateci a rendere la GWN migliore.</p>
	</body>
</chapter>
<chapter>
	<title>Informazioni per l'Iscrizione alla GWN</title>
	<body>
	<p>Per iscrivervi alla Gentoo Weekly Newsletter, mandate un email vuoto a <email>gentoo-gwn-subscribe@gentoo.org</email>.</p>
	<p>Per annullare l'iscrizione alla Gentoo Weekly Newsletter, mandate un email vuoto a <email>gentoo-gwn-unsubscribe@gentoo.org</email>dall'indirizzo email con il quale siete iscritti.</p>
	</body>
</chapter>
<chapter>
	<title>Other Languages</title>
	<body>
	<p>La Gentoo Weekly Newsletter è anche disponibile nei seguenti linguaggi:</p>
	<ul>
		<li><uri link="http://www.gentoo.org/news/be/gwn/gwn.xml">Olandese</uri></li>
		<li><uri link="http://www.gentoo.org/news/en/gwn/gwn.xml">Inglese</uri></li>
		<li><uri link="http://www.gentoo.org/news/de/gwn/gwn.xml">Tedesco</uri></li>
		<li><uri link="http://www.gentoo.org/news/fr/gwn/gwn.xml">Francese</uri></li>
		<li><uri link="http://www.gentoo.org/news/ja/gwn/gwn.xml">Giapponese</uri></li>
		<li><uri link="http://www.gentoo.org/news/it/gwn/gwn.xml">Italiano</uri></li>
		<li><uri link="http://www.gentoo.org/news/pl/gwn/gwn.xml">Polacco</uri></li>
		<li><uri link="http://www.gentoo.org/news/br/gwn/gwn.xml">Portoghese (Brasile)</uri></li>
		<li><uri link="http://www.gentoo.org/news/pt/gwn/gwn.xml">Portoghese (Portogallo)</uri></li>
		<li><uri link="http://www.gentoo.org/news/ru/gwn/gwn.xml">Russo</uri></li>
		<li><uri link="http://www.gentoo.org/news/es/gwn/gwn.xml">Spagnolo</uri></li>
		<li><uri link="http://www.gentoo.org/news/tr/gwn/gwn.xml">Turco</uri></li>
	</ul>
	</body>
</chapter>
</guide>
