<?xml version='1.0'?>

<news gentoo="yes" category="linux">
	<poster>klieber</poster>
	<date>16 June 2003</date>
	<title>Gentoo Weekly Newsletter -- June 16th, 2003</title>
<body>
<p>
<b>GLEPs and bugs headline <uri link="/news/en/gwn/20030616-newsletter.xml">this week's issue</uri> of the Gentoo Weekly Newsletter.</b>  Read on to learn more about these issues, along with User Stories, Bugzilla summaries and Heard in the Community.  Tips and Tricks is taking the week off, but will return in next week's issue.  Enjoy!
</p>
</body>
</news>
